trigger_informer_scan/__init__.py
trigger_informer_scan/trigger.py
trigger_informer_scan-0.2.dist-info/LICENSE
trigger_informer_scan-0.2.dist-info/METADATA
trigger_informer_scan-0.2.dist-info/WHEEL
trigger_informer_scan-0.2.dist-info/entry_points.txt
trigger_informer_scan-0.2.dist-info/top_level.txt
trigger_informer_scan-0.2.dist-info/RECORD
