Metadata-Version: 2.1
Name: trigger-informer-scan
Version: 0.2
Summary: Trigger scans in Informer via your CI/CD pipeline
Home-page: UNKNOWN
Author: Paul Collingwood
Author-email: paul.collingwood@informer.io
License: UNKNOWN
Platform: UNKNOWN
Classifier: Programming Language :: Python :: 3
Classifier: License :: OSI Approved :: MIT License
Classifier: Operating System :: OS Independent
Requires-Python: >=3.6
License-File: LICENSE
Requires-Dist: requests (>=2.25.1)
